setup.py
ContextFreeGrammar/ContextFreeGrammar.py
ContextFreeGrammar/Rule.py
ContextFreeGrammar/RuleType.py
ContextFreeGrammar/__init__.py
NlpToolkit_SyntacticParser.egg-info/PKG-INFO
NlpToolkit_SyntacticParser.egg-info/SOURCES.txt
NlpToolkit_SyntacticParser.egg-info/dependency_links.txt
NlpToolkit_SyntacticParser.egg-info/requires.txt
NlpToolkit_SyntacticParser.egg-info/top_level.txt
ProbabilisticContextFreeGrammar/ProbabilisticContextFreeGrammar.py
ProbabilisticContextFreeGrammar/ProbabilisticParseNode.py
ProbabilisticContextFreeGrammar/ProbabilisticRule.py
ProbabilisticContextFreeGrammar/__init__.py
ProbabilisticParser/ProbabilisticCYKParser.py
ProbabilisticParser/ProbabilisticParser.py
ProbabilisticParser/__init__.py
SyntacticParser/CYKParser.py
SyntacticParser/PartialParseList.py
SyntacticParser/SyntacticParser.py
SyntacticParser/__init__.py