Metadata-Version: 2.1
Name: NlpToolkit-SyntacticParser
Version: 1.0.0
Summary: Syntactic Parsing Algorithms
Home-page: https://github.com/StarlangSoftware/SyntacticParser-Py
Author: olcaytaner
Author-email: olcay.yildiz@ozyegin.edu.tr
